[
  {
    "componentHex": "FB2178EC",
    "component": 4213274860,
    "name": "",
    "categoryHex": "94B2E3AF",
    "category": 2494751663,
    "categoryName": "horse_bridles",
    "type": "1",
    "isMp": true,
    "isSp": false,
    "friendlyName": "",
    "palette": "metaped_tint_generic",
    "tint0": 42,
    "tint1": 0,
    "tint2": 88,
    "drawable": 2827014471,
    "albedo": 1428688478,
    "normal": 2547115921,
    "swatchTextureHex": "7A23FEFC",
    "swatchTexture": "uisw_cotton_000"
  },
  {
    "componentHex": "E006B4ED",
    "component": 3758535917,
    "name": "",
    "categoryHex": "94B2E3AF",
    "category": 2494751663,
    "categoryName": "horse_bridles",
    "type": "1",
    "isMp": true,
    "isSp": false,
    "friendlyName": "",
    "palette": "metaped_tint_combined_leather",
    "tint0": 122,
    "tint1": 221,
    "tint2": 129,
    "drawable": "mp_bridle_hr1_011",
    "albedo": "mp_bridle_hr1_011_c1_999_ab",
    "normal": "mp_bridle_hr1_011_c1_999_nm",
    "swatchTextureHex": "7C0FB811",
    "swatchTexture": "uisw_horse_leather_new000"
  },
  {
    "componentHex": "D1D7988F",
    "component": 3520567439,
    "name": "",
    "categoryHex": "94B2E3AF",
    "category": 2494751663,
    "categoryName": "horse_bridles",
    "type": "1",
    "isMp": true,
    "isSp": false,
    "friendlyName": "",
    "palette": "metaped_tint_combined_leather",
    "tint0": 17,
    "tint1": 144,
    "tint2": 146,
    "drawable": "mp_bridle_hr1_011",
    "albedo": "mp_bridle_hr1_011_c1_999_ab",
    "normal": "mp_bridle_hr1_011_c1_999_nm",
    "swatchTextureHex": "7C0FB811",
    "swatchTexture": "uisw_horse_leather_new000"
  },
  {
    "componentHex": "0CBA8E54",
    "component": 213552724,
    "name": "",
    "categoryHex": "94B2E3AF",
    "category": 2494751663,
    "categoryName": "horse_bridles",
    "type": "1",
    "isMp": true,
    "isSp": false,
    "friendlyName": "",
    "palette": "metaped_tint_combined_leather",
    "tint0": 166,
    "tint1": 41,
    "tint2": 199,
    "drawable": "mp_bridle_hr1_011",
    "albedo": "mp_bridle_hr1_011_c1_999_ab",
    "normal": "mp_bridle_hr1_011_c1_999_nm",
    "swatchTextureHex": "7C0FB811",
    "swatchTexture": "uisw_horse_leather_new000"
  },
  {
    "componentHex": "2F62D3A4",
    "component": 795005860,
    "name": "",
    "categoryHex": "94B2E3AF",
    "category": 2494751663,
    "categoryName": "horse_bridles",
    "type": "1",
    "isMp": true,
    "isSp": false,
    "friendlyName": "",
    "palette": "metaped_tint_combined_leather",
    "tint0": 142,
    "tint1": 131,
    "tint2": 44,
    "drawable": "mp_bridle_hr1_011",
    "albedo": "mp_bridle_hr1_011_c1_999_ab",
    "normal": "mp_bridle_hr1_011_c1_999_nm",
    "swatchTextureHex": "7C0FB811",
    "swatchTexture": "uisw_horse_leather_new000"
  },
  {
    "componentHex": "7E89F1D9",
    "component": 2122969561,
    "name": "",
    "categoryHex": "94B2E3AF",
    "category": 2494751663,
    "categoryName": "horse_bridles",
    "type": "1",
    "isMp": true,
    "isSp": false,
    "friendlyName": "",
    "palette": "metaped_tint_combined_leather",
    "tint0": 226,
    "tint1": 150,
    "tint2": 173,
    "drawable": "mp_bridle_hr1_011",
    "albedo": "mp_bridle_hr1_011_c1_999_ab",
    "normal": "mp_bridle_hr1_011_c1_999_nm",
    "swatchTextureHex": "7C0FB811",
    "swatchTexture": "uisw_horse_leather_new000"
  },
  {
    "componentHex": "5BC3AC4D",
    "component": 1539550285,
    "name": "",
    "categoryHex": "94B2E3AF",
    "category": 2494751663,
    "categoryName": "horse_bridles",
    "type": "1",
    "isMp": true,
    "isSp": false,
    "friendlyName": "",
    "palette": "metaped_tint_combined_leather",
    "tint0": 194,
    "tint1": 90,
    "tint2": 138,
    "drawable": "mp_bridle_hr1_011",
    "albedo": "mp_bridle_hr1_011_c1_999_ab",
    "normal": "mp_bridle_hr1_011_c1_999_nm",
    "swatchTextureHex": "7C0FB811",
    "swatchTexture": "uisw_horse_leather_new000"
  },
  {
    "componentHex": "AAA9CA18",
    "component": 2863254040,
    "name": "",
    "categoryHex": "94B2E3AF",
    "category": 2494751663,
    "categoryName": "horse_bridles",
    "type": "1",
    "isMp": true,
    "isSp": false,
    "friendlyName": "",
    "palette": "metaped_tint_combined_leather",
    "tint0": 206,
    "tint1": 219,
    "tint2": 137,
    "drawable": "mp_bridle_hr1_011",
    "albedo": "mp_bridle_hr1_011_c1_999_ab",
    "normal": "mp_bridle_hr1_011_c1_999_nm",
    "swatchTextureHex": "7C0FB811",
    "swatchTexture": "uisw_horse_leather_new000"
  },
  {
    "componentHex": "B8F0E6A6",
    "component": 3102795430,
    "name": "",
    "categoryHex": "94B2E3AF",
    "category": 2494751663,
    "categoryName": "horse_bridles",
    "type": "1",
    "isMp": true,
    "isSp": false,
    "friendlyName": "",
    "palette": "metaped_tint_combined_leather",
    "tint0": 248,
    "tint1": 133,
    "tint2": 167,
    "drawable": "mp_bridle_hr1_011",
    "albedo": "mp_bridle_hr1_011_c1_999_ab",
    "normal": "mp_bridle_hr1_011_c1_999_nm",
    "swatchTextureHex": "7C0FB811",
    "swatchTexture": "uisw_horse_leather_new000"
  },
  {
    "componentHex": "874F0363",
    "component": 2270102371,
    "name": "",
    "categoryHex": "94B2E3AF",
    "category": 2494751663,
    "categoryName": "horse_bridles",
    "type": "1",
    "isMp": true,
    "isSp": false,
    "friendlyName": "",
    "palette": "metaped_tint_combined_leather",
    "tint0": 131,
    "tint1": 186,
    "tint2": 154,
    "drawable": "mp_bridle_hr1_011",
    "albedo": "mp_bridle_hr1_011_c1_999_ab",
    "normal": "mp_bridle_hr1_011_c1_999_nm",
    "swatchTextureHex": "7C0FB811",
    "swatchTexture": "uisw_horse_leather_new000"
  },
  {
    "componentHex": "95ADA020",
    "component": 2511183904,
    "name": "",
    "categoryHex": "94B2E3AF",
    "category": 2494751663,
    "categoryName": "horse_bridles",
    "type": "1",
    "isMp": true,
    "isSp": false,
    "friendlyName": "",
    "palette": "metaped_tint_combined_leather",
    "tint0": 134,
    "tint1": 6,
    "tint2": 47,
    "drawable": "mp_bridle_hr1_011",
    "albedo": "mp_bridle_hr1_011_c1_999_ab",
    "normal": "mp_bridle_hr1_011_c1_999_nm",
    "swatchTextureHex": "7C0FB811",
    "swatchTexture": "uisw_horse_leather_new000"
  },
  {
    "componentHex": "FE8E56EC",
    "component": 4270741228,
    "name": "",
    "categoryHex": "94B2E3AF",
    "category": 2494751663,
    "categoryName": "horse_bridles",
    "type": "1",
    "isMp": true,
    "isSp": false,
    "friendlyName": "",
    "palette": "metaped_tint_combined_leather",
    "tint0": 199,
    "tint1": 59,
    "tint2": 108,
    "drawable": "mp_bridle_hr1_012",
    "albedo": "mp_bridle_hr1_012_c1_001_ab",
    "normal": "mp_bridle_hr1_012_c1_001_nm",
    "swatchTextureHex": "7C0FB811",
    "swatchTexture": "uisw_horse_leather_new000"
  },
  {
    "componentHex": "0C48F261",
    "component": 206107233,
    "name": "",
    "categoryHex": "94B2E3AF",
    "category": 2494751663,
    "categoryName": "horse_bridles",
    "type": "1",
    "isMp": true,
    "isSp": false,
    "friendlyName": "",
    "palette": "metaped_tint_combined_leather",
    "tint0": 27,
    "tint1": 75,
    "tint2": 61,
    "drawable": "mp_bridle_hr1_012",
    "albedo": "mp_bridle_hr1_012_c1_002_ab",
    "normal": "mp_bridle_hr1_012_c1_001_nm",
    "swatchTextureHex": "7C0FB811",
    "swatchTexture": "uisw_horse_leather_new000"
  },
  {
    "componentHex": "E3139FF7",
    "component": 3809714167,
    "name": "",
    "categoryHex": "94B2E3AF",
    "category": 2494751663,
    "categoryName": "horse_bridles",
    "type": "1",
    "isMp": true,
    "isSp": false,
    "friendlyName": "",
    "palette": "metaped_tint_combined_leather",
    "tint0": 58,
    "tint1": 230,
    "tint2": 234,
    "drawable": "mp_bridle_hr1_012",
    "albedo": "mp_bridle_hr1_012_c1_003_ab",
    "normal": "mp_bridle_hr1_012_c1_001_nm",
    "swatchTextureHex": "7C0FB811",
    "swatchTexture": "uisw_horse_leather_new000"
  },
  {
    "componentHex": "F0D53B7A",
    "component": 4040506234,
    "name": "",
    "categoryHex": "94B2E3AF",
    "category": 2494751663,
    "categoryName": "horse_bridles",
    "type": "1",
    "isMp": true,
    "isSp": false,
    "friendlyName": "",
    "palette": "metaped_tint_combined_leather",
    "tint0": 102,
    "tint1": 200,
    "tint2": 0,
    "drawable": "mp_bridle_hr1_012",
    "albedo": "mp_bridle_hr1_012_c1_004_ab",
    "normal": "mp_bridle_hr1_012_c1_001_nm",
    "swatchTextureHex": "7C0FB811",
    "swatchTexture": "uisw_horse_leather_new000"
  },
  {
    "componentHex": "433DE046",
    "component": 1128128582,
    "name": "",
    "categoryHex": "94B2E3AF",
    "category": 2494751663,
    "categoryName": "horse_bridles",
    "type": "1",
    "isMp": true,
    "isSp": false,
    "friendlyName": "",
    "palette": "metaped_tint_combined_leather",
    "tint0": 167,
    "tint1": 171,
    "tint2": 229,
    "drawable": "mp_bridle_hr1_012",
    "albedo": "mp_bridle_hr1_012_c1_005_ab",
    "normal": "mp_bridle_hr1_012_c1_001_nm",
    "swatchTextureHex": "7C0FB811",
    "swatchTexture": "uisw_horse_leather_new000"
  },
  {
    "componentHex": "F18C3CE4",
    "component": 4052499684,
    "name": "",
    "categoryHex": "94B2E3AF",
    "category": 2494751663,
    "categoryName": "horse_bridles",
    "type": "1",
    "isMp": true,
    "isSp": false,
    "friendlyName": "",
    "palette": "metaped_tint_combined_leather",
    "tint0": 55,
    "tint1": 81,
    "tint2": 133,
    "drawable": "mp_bridle_hr1_012",
    "albedo": "mp_bridle_hr1_012_c1_006_ab",
    "normal": "mp_bridle_hr1_012_c1_001_nm",
    "swatchTextureHex": "7C0FB811",
    "swatchTexture": "uisw_horse_leather_new000"
  },
  {
    "componentHex": "CFFBF4B5",
    "component": 3489395893,
    "name": "",
    "categoryHex": "94B2E3AF",
    "category": 2494751663,
    "categoryName": "horse_bridles",
    "type": "1",
    "isMp": true,
    "isSp": false,
    "friendlyName": "",
    "palette": "metaped_tint_combined_leather",
    "tint0": 12,
    "tint1": 147,
    "tint2": 54,
    "drawable": "mp_bridle_hr1_013",
    "albedo": "mp_bridle_hr1_013_c1_001_ab",
    "normal": "mp_bridle_hr1_013_c1_001_nm",
    "swatchTextureHex": "7C0FB811",
    "swatchTexture": "uisw_horse_leather_new000"
  },
  {
    "componentHex": "63899BC6",
    "component": 1669962694,
    "name": "",
    "categoryHex": "94B2E3AF",
    "category": 2494751663,
    "categoryName": "horse_bridles",
    "type": "1",
    "isMp": true,
    "isSp": false,
    "friendlyName": "",
    "palette": "metaped_tint_combined_leather",
    "tint0": 60,
    "tint1": 195,
    "tint2": 186,
    "drawable": "mp_bridle_hr1_013",
    "albedo": "mp_bridle_hr1_013_c1_002_ab",
    "normal": "mp_bridle_hr1_013_c1_001_nm",
    "swatchTextureHex": "7C0FB811",
    "swatchTexture": "uisw_horse_leather_new000"
  },
  {
    "componentHex": "754C3F4B",
    "component": 1967931211,
    "name": "",
    "categoryHex": "94B2E3AF",
    "category": 2494751663,
    "categoryName": "horse_bridles",
    "type": "1",
    "isMp": true,
    "isSp": false,
    "friendlyName": "",
    "palette": "metaped_tint_combined_leather",
    "tint0": 185,
    "tint1": 144,
    "tint2": 181,
    "drawable": "mp_bridle_hr1_013",
    "albedo": "mp_bridle_hr1_013_c1_003_ab",
    "normal": "mp_bridle_hr1_013_c1_001_nm",
    "swatchTextureHex": "7C0FB811",
    "swatchTexture": "uisw_horse_leather_new000"
  },
  {
    "componentHex": "7956475F",
    "component": 2035697503,
    "name": "",
    "categoryHex": "94B2E3AF",
    "category": 2494751663,
    "categoryName": "horse_bridles",
    "type": "1",
    "isMp": true,
    "isSp": false,
    "friendlyName": "",
    "palette": "metaped_tint_combined_leather",
    "tint0": 230,
    "tint1": 122,
    "tint2": 225,
    "drawable": "mp_bridle_hr1_013",
    "albedo": "mp_bridle_hr1_013_c1_004_ab",
    "normal": "mp_bridle_hr1_013_c1_001_nm",
    "swatchTextureHex": "7C0FB811",
    "swatchTexture": "uisw_horse_leather_new000"
  },
  {
    "componentHex": "880FE4D2",
    "component": 2282742994,
    "name": "",
    "categoryHex": "94B2E3AF",
    "category": 2494751663,
    "categoryName": "horse_bridles",
    "type": "1",
    "isMp": true,
    "isSp": false,
    "friendlyName": "",
    "palette": "metaped_tint_combined_leather",
    "tint0": 17,
    "tint1": 138,
    "tint2": 75,
    "drawable": "mp_bridle_hr1_013",
    "albedo": "mp_bridle_hr1_013_c1_005_ab",
    "normal": "mp_bridle_hr1_013_c1_001_nm",
    "swatchTextureHex": "7C0FB811",
    "swatchTexture": "uisw_horse_leather_new000"
  },
  {
    "componentHex": "1A7E09B0",
    "component": 444467632,
    "name": "",
    "categoryHex": "94B2E3AF",
    "category": 2494751663,
    "categoryName": "horse_bridles",
    "type": "1",
    "isMp": true,
    "isSp": false,
    "friendlyName": "",
    "palette": "metaped_tint_combined_leather",
    "tint0": 45,
    "tint1": 53,
    "tint2": 188,
    "drawable": 1076761915,
    "albedo": 1136976259,
    "normal": 659380532,
    "swatchTextureHex": "7C0FB811",
    "swatchTexture": "uisw_horse_leather_new000"
  }
]